[
  {
    "ASVS": "v5.0.0-1.1.1",
    "Level": 2,
    "Chapter": "Encoding and Sanitization",
    "Applicability": "Applicable L2",
    "Component": "Starlim ERP",
    "Verification": "automated/manual evidence where available",
    "Status": "NOT_TESTED",
    "Evidence": "No direct evidence in this pass",
    "Finding": "",
    "Recommendation": "See roadmap"
  },
  {
    "ASVS": "v5.0.0-1.1.2",
    "Level": 2,
    "Chapter": "Encoding and Sanitization",
    "Applicability": "Applicable L2",
    "Component": "Starlim ERP",
    "Verification": "automated/manual evidence where available",
    "Status": "NOT_TESTED",
    "Evidence": "No direct evidence in this pass",
    "Finding": "",
    "Recommendation": "See roadmap"
  },
  {
    "ASVS": "v5.0.0-1.2.6",
    "Level": 2,
    "Chapter": "Encoding and Sanitization",
    "Applicability": "Applicable L2",
    "Component": "Starlim ERP",
    "Verification": "automated/manual evidence where available",
    "Status": "NOT_TESTED",
    "Evidence": "No direct evidence in this pass",
    "Finding": "",
    "Recommendation": "See roadmap"
  },
  {
    "ASVS": "v5.0.0-1.2.7",
    "Level": 2,
    "Chapter": "Encoding and Sanitization",
    "Applicability": "Applicable L2",
    "Component": "Starlim ERP",
    "Verification": "automated/manual evidence where available",
    "Status": "NOT_TESTED",
    "Evidence": "No direct evidence in this pass",
    "Finding": "",
    "Recommendation": "See roadmap"
  },
  {
    "ASVS": "v5.0.0-1.2.8",
    "Level": 2,
    "Chapter": "Encoding and Sanitization",
    "Applicability": "Applicable L2",
    "Component": "Starlim ERP",
    "Verification": "automated/manual evidence where available",
    "Status": "NOT_TESTED",
    "Evidence": "No direct evidence in this pass",
    "Finding": "",
    "Recommendation": "See roadmap"
  },
  {
    "ASVS": "v5.0.0-1.2.9",
    "Level": 2,
    "Chapter": "Encoding and Sanitization",
    "Applicability": "Applicable L2",
    "Component": "Starlim ERP",
    "Verification": "automated/manual evidence where available",
    "Status": "NOT_TESTED",
    "Evidence": "No direct evidence in this pass",
    "Finding": "",
    "Recommendation": "See roadmap"
  },
  {
    "ASVS": "v5.0.0-1.3.3",
    "Level": 2,
    "Chapter": "Encoding and Sanitization",
    "Applicability": "Applicable L2",
    "Component": "Starlim ERP",
    "Verification": "automated/manual evidence where available",
    "Status": "NOT_TESTED",
    "Evidence": "No direct evidence in this pass",
    "Finding": "",
    "Recommendation": "See roadmap"
  },
  {
    "ASVS": "v5.0.0-1.3.4",
    "Level": 2,
    "Chapter": "Encoding and Sanitization",
    "Applicability": "Applicable L2",
    "Component": "Starlim ERP",
    "Verification": "automated/manual evidence where available",
    "Status": "NOT_TESTED",
    "Evidence": "No direct evidence in this pass",
    "Finding": "",
    "Recommendation": "See roadmap"
  },
  {
    "ASVS": "v5.0.0-1.3.5",
    "Level": 2,
    "Chapter": "Encoding and Sanitization",
    "Applicability": "Applicable L2",
    "Component": "Starlim ERP",
    "Verification": "automated/manual evidence where available",
    "Status": "NOT_TESTED",
    "Evidence": "No direct evidence in this pass",
    "Finding": "",
    "Recommendation": "See roadmap"
  },
  {
    "ASVS": "v5.0.0-1.3.6",
    "Level": 2,
    "Chapter": "Encoding and Sanitization",
    "Applicability": "Applicable L2",
    "Component": "Starlim ERP",
    "Verification": "automated/manual evidence where available",
    "Status": "NOT_TESTED",
    "Evidence": "No direct evidence in this pass",
    "Finding": "",
    "Recommendation": "See roadmap"
  },
  {
    "ASVS": "v5.0.0-1.3.7",
    "Level": 2,
    "Chapter": "Encoding and Sanitization",
    "Applicability": "Applicable L2",
    "Component": "Starlim ERP",
    "Verification": "automated/manual evidence where available",
    "Status": "NOT_TESTED",
    "Evidence": "No direct evidence in this pass",
    "Finding": "",
    "Recommendation": "See roadmap"
  },
  {
    "ASVS": "v5.0.0-1.3.8",
    "Level": 2,
    "Chapter": "Encoding and Sanitization",
    "Applicability": "Applicable L2",
    "Component": "Starlim ERP",
    "Verification": "automated/manual evidence where available",
    "Status": "NOT_TESTED",
    "Evidence": "No direct evidence in this pass",
    "Finding": "",
    "Recommendation": "See roadmap"
  },
  {
    "ASVS": "v5.0.0-1.3.9",
    "Level": 2,
    "Chapter": "Encoding and Sanitization",
    "Applicability": "Applicable L2",
    "Component": "Starlim ERP",
    "Verification": "automated/manual evidence where available",
    "Status": "NOT_TESTED",
    "Evidence": "No direct evidence in this pass",
    "Finding": "",
    "Recommendation": "See roadmap"
  },
  {
    "ASVS": "v5.0.0-1.3.10",
    "Level": 2,
    "Chapter": "Encoding and Sanitization",
    "Applicability": "Applicable L2",
    "Component": "Starlim ERP",
    "Verification": "automated/manual evidence where available",
    "Status": "NOT_TESTED",
    "Evidence": "No direct evidence in this pass",
    "Finding": "",
    "Recommendation": "See roadmap"
  },
  {
    "ASVS": "v5.0.0-1.3.11",
    "Level": 2,
    "Chapter": "Encoding and Sanitization",
    "Applicability": "Applicable L2",
    "Component": "Starlim ERP",
    "Verification": "automated/manual evidence where available",
    "Status": "NOT_TESTED",
    "Evidence": "No direct evidence in this pass",
    "Finding": "",
    "Recommendation": "See roadmap"
  },
  {
    "ASVS": "v5.0.0-1.4.1",
    "Level": 2,
    "Chapter": "Encoding and Sanitization",
    "Applicability": "Applicable L2",
    "Component": "Starlim ERP",
    "Verification": "automated/manual evidence where available",
    "Status": "NOT_TESTED",
    "Evidence": "No direct evidence in this pass",
    "Finding": "",
    "Recommendation": "See roadmap"
  },
  {
    "ASVS": "v5.0.0-1.4.2",
    "Level": 2,
    "Chapter": "Encoding and Sanitization",
    "Applicability": "Applicable L2",
    "Component": "Starlim ERP",
    "Verification": "automated/manual evidence where available",
    "Status": "NOT_TESTED",
    "Evidence": "No direct evidence in this pass",
    "Finding": "",
    "Recommendation": "See roadmap"
  },
  {
    "ASVS": "v5.0.0-1.4.3",
    "Level": 2,
    "Chapter": "Encoding and Sanitization",
    "Applicability": "Applicable L2",
    "Component": "Starlim ERP",
    "Verification": "automated/manual evidence where available",
    "Status": "NOT_TESTED",
    "Evidence": "No direct evidence in this pass",
    "Finding": "",
    "Recommendation": "See roadmap"
  },
  {
    "ASVS": "v5.0.0-1.5.2",
    "Level": 2,
    "Chapter": "Encoding and Sanitization",
    "Applicability": "Applicable L2",
    "Component": "Starlim ERP",
    "Verification": "automated/manual evidence where available",
    "Status": "NOT_TESTED",
    "Evidence": "No direct evidence in this pass",
    "Finding": "",
    "Recommendation": "See roadmap"
  },
  {
    "ASVS": "v5.0.0-2.1.2",
    "Level": 2,
    "Chapter": "Validation and Business Logic",
    "Applicability": "Applicable L2",
    "Component": "Starlim ERP",
    "Verification": "automated/manual evidence where available",
    "Status": "NOT_TESTED",
    "Evidence": "No direct evidence in this pass",
    "Finding": "",
    "Recommendation": "See roadmap"
  },
  {
    "ASVS": "v5.0.0-2.1.3",
    "Level": 2,
    "Chapter": "Validation and Business Logic",
    "Applicability": "Applicable L2",
    "Component": "Starlim ERP",
    "Verification": "automated/manual evidence where available",
    "Status": "NOT_TESTED",
    "Evidence": "No direct evidence in this pass",
    "Finding": "",
    "Recommendation": "See roadmap"
  },
  {
    "ASVS": "v5.0.0-2.2.3",
    "Level": 2,
    "Chapter": "Validation and Business Logic",
    "Applicability": "Applicable L2",
    "Component": "Starlim ERP",
    "Verification": "automated/manual evidence where available",
    "Status": "NOT_TESTED",
    "Evidence": "No direct evidence in this pass",
    "Finding": "",
    "Recommendation": "See roadmap"
  },
  {
    "ASVS": "v5.0.0-2.3.2",
    "Level": 2,
    "Chapter": "Validation and Business Logic",
    "Applicability": "Applicable L2",
    "Component": "Starlim ERP",
    "Verification": "automated/manual evidence where available",
    "Status": "NOT_TESTED",
    "Evidence": "No direct evidence in this pass",
    "Finding": "",
    "Recommendation": "See roadmap"
  },
  {
    "ASVS": "v5.0.0-2.3.3",
    "Level": 2,
    "Chapter": "Validation and Business Logic",
    "Applicability": "Applicable L2",
    "Component": "Starlim ERP",
    "Verification": "automated/manual evidence where available",
    "Status": "NOT_TESTED",
    "Evidence": "No direct evidence in this pass",
    "Finding": "",
    "Recommendation": "See roadmap"
  },
  {
    "ASVS": "v5.0.0-2.3.4",
    "Level": 2,
    "Chapter": "Validation and Business Logic",
    "Applicability": "Applicable L2",
    "Component": "Starlim ERP",
    "Verification": "automated/manual evidence where available",
    "Status": "NOT_TESTED",
    "Evidence": "No direct evidence in this pass",
    "Finding": "",
    "Recommendation": "See roadmap"
  },
  {
    "ASVS": "v5.0.0-2.4.1",
    "Level": 2,
    "Chapter": "Validation and Business Logic",
    "Applicability": "Applicable L2",
    "Component": "Starlim ERP",
    "Verification": "automated/manual evidence where available",
    "Status": "NOT_TESTED",
    "Evidence": "No direct evidence in this pass",
    "Finding": "",
    "Recommendation": "See roadmap"
  },
  {
    "ASVS": "v5.0.0-3.3.2",
    "Level": 2,
    "Chapter": "Web Frontend Security",
    "Applicability": "Applicable L2",
    "Component": "Starlim ERP",
    "Verification": "automated/manual evidence where available",
    "Status": "PASS",
    "Evidence": "CHK-SESSION-001",
    "Finding": "",
    "Recommendation": "See roadmap"
  },
  {
    "ASVS": "v5.0.0-3.3.3",
    "Level": 2,
    "Chapter": "Web Frontend Security",
    "Applicability": "Applicable L2",
    "Component": "Starlim ERP",
    "Verification": "automated/manual evidence where available",
    "Status": "NOT_TESTED",
    "Evidence": "No direct evidence in this pass",
    "Finding": "",
    "Recommendation": "See roadmap"
  },
  {
    "ASVS": "v5.0.0-3.3.4",
    "Level": 2,
    "Chapter": "Web Frontend Security",
    "Applicability": "Applicable L2",
    "Component": "Starlim ERP",
    "Verification": "automated/manual evidence where available",
    "Status": "PASS",
    "Evidence": "CHK-SESSION-001",
    "Finding": "",
    "Recommendation": "See roadmap"
  },
  {
    "ASVS": "v5.0.0-3.4.3",
    "Level": 2,
    "Chapter": "Web Frontend Security",
    "Applicability": "Applicable L2",
    "Component": "Starlim ERP",
    "Verification": "automated/manual evidence where available",
    "Status": "NOT_TESTED",
    "Evidence": "No direct evidence in this pass",
    "Finding": "",
    "Recommendation": "See roadmap"
  },
  {
    "ASVS": "v5.0.0-3.4.4",
    "Level": 2,
    "Chapter": "Web Frontend Security",
    "Applicability": "Applicable L2",
    "Component": "Starlim ERP",
    "Verification": "automated/manual evidence where available",
    "Status": "NOT_TESTED",
    "Evidence": "No direct evidence in this pass",
    "Finding": "",
    "Recommendation": "See roadmap"
  },
  {
    "ASVS": "v5.0.0-3.4.5",
    "Level": 2,
    "Chapter": "Web Frontend Security",
    "Applicability": "Applicable L2",
    "Component": "Starlim ERP",
    "Verification": "automated/manual evidence where available",
    "Status": "NOT_TESTED",
    "Evidence": "No direct evidence in this pass",
    "Finding": "",
    "Recommendation": "See roadmap"
  },
  {
    "ASVS": "v5.0.0-3.4.6",
    "Level": 2,
    "Chapter": "Web Frontend Security",
    "Applicability": "Applicable L2",
    "Component": "Starlim ERP",
    "Verification": "automated/manual evidence where available",
    "Status": "NOT_TESTED",
    "Evidence": "No direct evidence in this pass",
    "Finding": "",
    "Recommendation": "See roadmap"
  },
  {
    "ASVS": "v5.0.0-3.5.4",
    "Level": 2,
    "Chapter": "Web Frontend Security",
    "Applicability": "Applicable L2",
    "Component": "Starlim ERP",
    "Verification": "automated/manual evidence where available",
    "Status": "NOT_TESTED",
    "Evidence": "No direct evidence in this pass",
    "Finding": "",
    "Recommendation": "See roadmap"
  },
  {
    "ASVS": "v5.0.0-3.5.5",
    "Level": 2,
    "Chapter": "Web Frontend Security",
    "Applicability": "Applicable L2",
    "Component": "Starlim ERP",
    "Verification": "automated/manual evidence where available",
    "Status": "NOT_TESTED",
    "Evidence": "No direct evidence in this pass",
    "Finding": "",
    "Recommendation": "See roadmap"
  },
  {
    "ASVS": "v5.0.0-3.7.1",
    "Level": 2,
    "Chapter": "Web Frontend Security",
    "Applicability": "Applicable L2",
    "Component": "Starlim ERP",
    "Verification": "automated/manual evidence where available",
    "Status": "NOT_TESTED",
    "Evidence": "No direct evidence in this pass",
    "Finding": "",
    "Recommendation": "See roadmap"
  },
  {
    "ASVS": "v5.0.0-3.7.2",
    "Level": 2,
    "Chapter": "Web Frontend Security",
    "Applicability": "Applicable L2",
    "Component": "Starlim ERP",
    "Verification": "automated/manual evidence where available",
    "Status": "NOT_TESTED",
    "Evidence": "No direct evidence in this pass",
    "Finding": "",
    "Recommendation": "See roadmap"
  },
  {
    "ASVS": "v5.0.0-4.1.2",
    "Level": 2,
    "Chapter": "API and Web Service",
    "Applicability": "Applicable L2",
    "Component": "Starlim ERP",
    "Verification": "automated/manual evidence where available",
    "Status": "NOT_TESTED",
    "Evidence": "No direct evidence in this pass",
    "Finding": "",
    "Recommendation": "See roadmap"
  },
  {
    "ASVS": "v5.0.0-4.1.3",
    "Level": 2,
    "Chapter": "API and Web Service",
    "Applicability": "Applicable L2",
    "Component": "Starlim ERP",
    "Verification": "automated/manual evidence where available",
    "Status": "NOT_TESTED",
    "Evidence": "No direct evidence in this pass",
    "Finding": "",
    "Recommendation": "See roadmap"
  },
  {
    "ASVS": "v5.0.0-4.2.1",
    "Level": 2,
    "Chapter": "API and Web Service",
    "Applicability": "Applicable L2",
    "Component": "Starlim ERP",
    "Verification": "automated/manual evidence where available",
    "Status": "NOT_TESTED",
    "Evidence": "No direct evidence in this pass",
    "Finding": "",
    "Recommendation": "See roadmap"
  },
  {
    "ASVS": "v5.0.0-4.3.1",
    "Level": 2,
    "Chapter": "API and Web Service",
    "Applicability": "Applicable L2",
    "Component": "Starlim ERP",
    "Verification": "automated/manual evidence where available",
    "Status": "NOT_TESTED",
    "Evidence": "No direct evidence in this pass",
    "Finding": "",
    "Recommendation": "See roadmap"
  },
  {
    "ASVS": "v5.0.0-4.3.2",
    "Level": 2,
    "Chapter": "API and Web Service",
    "Applicability": "Applicable L2",
    "Component": "Starlim ERP",
    "Verification": "automated/manual evidence where available",
    "Status": "NOT_TESTED",
    "Evidence": "No direct evidence in this pass",
    "Finding": "",
    "Recommendation": "See roadmap"
  },
  {
    "ASVS": "v5.0.0-4.4.2",
    "Level": 2,
    "Chapter": "API and Web Service",
    "Applicability": "Applicable L2",
    "Component": "Starlim ERP",
    "Verification": "automated/manual evidence where available",
    "Status": "NOT_TESTED",
    "Evidence": "No direct evidence in this pass",
    "Finding": "",
    "Recommendation": "See roadmap"
  },
  {
    "ASVS": "v5.0.0-4.4.3",
    "Level": 2,
    "Chapter": "API and Web Service",
    "Applicability": "Applicable L2",
    "Component": "Starlim ERP",
    "Verification": "automated/manual evidence where available",
    "Status": "NOT_TESTED",
    "Evidence": "No direct evidence in this pass",
    "Finding": "",
    "Recommendation": "See roadmap"
  },
  {
    "ASVS": "v5.0.0-4.4.4",
    "Level": 2,
    "Chapter": "API and Web Service",
    "Applicability": "Applicable L2",
    "Component": "Starlim ERP",
    "Verification": "automated/manual evidence where available",
    "Status": "NOT_TESTED",
    "Evidence": "No direct evidence in this pass",
    "Finding": "",
    "Recommendation": "See roadmap"
  },
  {
    "ASVS": "v5.0.0-5.1.1",
    "Level": 2,
    "Chapter": "File Handling",
    "Applicability": "Applicable L2",
    "Component": "Starlim ERP",
    "Verification": "automated/manual evidence where available",
    "Status": "NOT_TESTED",
    "Evidence": "No direct evidence in this pass",
    "Finding": "",
    "Recommendation": "See roadmap"
  },
  {
    "ASVS": "v5.0.0-5.2.3",
    "Level": 2,
    "Chapter": "File Handling",
    "Applicability": "Applicable L2",
    "Component": "Starlim ERP",
    "Verification": "automated/manual evidence where available",
    "Status": "NOT_TESTED",
    "Evidence": "No direct evidence in this pass",
    "Finding": "",
    "Recommendation": "See roadmap"
  },
  {
    "ASVS": "v5.0.0-5.4.1",
    "Level": 2,
    "Chapter": "File Handling",
    "Applicability": "Applicable L2",
    "Component": "Starlim ERP",
    "Verification": "automated/manual evidence where available",
    "Status": "NOT_TESTED",
    "Evidence": "No direct evidence in this pass",
    "Finding": "",
    "Recommendation": "See roadmap"
  },
  {
    "ASVS": "v5.0.0-5.4.2",
    "Level": 2,
    "Chapter": "File Handling",
    "Applicability": "Applicable L2",
    "Component": "Starlim ERP",
    "Verification": "automated/manual evidence where available",
    "Status": "NOT_TESTED",
    "Evidence": "No direct evidence in this pass",
    "Finding": "",
    "Recommendation": "See roadmap"
  },
  {
    "ASVS": "v5.0.0-5.4.3",
    "Level": 2,
    "Chapter": "File Handling",
    "Applicability": "Applicable L2",
    "Component": "Starlim ERP",
    "Verification": "automated/manual evidence where available",
    "Status": "NOT_TESTED",
    "Evidence": "No direct evidence in this pass",
    "Finding": "",
    "Recommendation": "See roadmap"
  },
  {
    "ASVS": "v5.0.0-6.1.2",
    "Level": 2,
    "Chapter": "Authentication",
    "Applicability": "Applicable L2",
    "Component": "Starlim ERP",
    "Verification": "automated/manual evidence where available",
    "Status": "NOT_TESTED",
    "Evidence": "No direct evidence in this pass",
    "Finding": "",
    "Recommendation": "See roadmap"
  },
  {
    "ASVS": "v5.0.0-6.1.3",
    "Level": 2,
    "Chapter": "Authentication",
    "Applicability": "Applicable L2",
    "Component": "Starlim ERP",
    "Verification": "automated/manual evidence where available",
    "Status": "NOT_TESTED",
    "Evidence": "No direct evidence in this pass",
    "Finding": "",
    "Recommendation": "See roadmap"
  },
  {
    "ASVS": "v5.0.0-6.2.9",
    "Level": 2,
    "Chapter": "Authentication",
    "Applicability": "Applicable L2",
    "Component": "Starlim ERP",
    "Verification": "automated/manual evidence where available",
    "Status": "NOT_TESTED",
    "Evidence": "No direct evidence in this pass",
    "Finding": "",
    "Recommendation": "See roadmap"
  },
  {
    "ASVS": "v5.0.0-6.2.10",
    "Level": 2,
    "Chapter": "Authentication",
    "Applicability": "Applicable L2",
    "Component": "Starlim ERP",
    "Verification": "automated/manual evidence where available",
    "Status": "NOT_TESTED",
    "Evidence": "No direct evidence in this pass",
    "Finding": "",
    "Recommendation": "See roadmap"
  },
  {
    "ASVS": "v5.0.0-6.2.11",
    "Level": 2,
    "Chapter": "Authentication",
    "Applicability": "Applicable L2",
    "Component": "Starlim ERP",
    "Verification": "automated/manual evidence where available",
    "Status": "NOT_TESTED",
    "Evidence": "No direct evidence in this pass",
    "Finding": "",
    "Recommendation": "See roadmap"
  },
  {
    "ASVS": "v5.0.0-6.2.12",
    "Level": 2,
    "Chapter": "Authentication",
    "Applicability": "Applicable L2",
    "Component": "Starlim ERP",
    "Verification": "automated/manual evidence where available",
    "Status": "NOT_TESTED",
    "Evidence": "No direct evidence in this pass",
    "Finding": "",
    "Recommendation": "See roadmap"
  },
  {
    "ASVS": "v5.0.0-6.3.3",
    "Level": 2,
    "Chapter": "Authentication",
    "Applicability": "Applicable L2",
    "Component": "Starlim ERP",
    "Verification": "automated/manual evidence where available",
    "Status": "NOT_TESTED",
    "Evidence": "No direct evidence in this pass",
    "Finding": "",
    "Recommendation": "See roadmap"
  },
  {
    "ASVS": "v5.0.0-6.3.4",
    "Level": 2,
    "Chapter": "Authentication",
    "Applicability": "Applicable L2",
    "Component": "Starlim ERP",
    "Verification": "automated/manual evidence where available",
    "Status": "NOT_TESTED",
    "Evidence": "No direct evidence in this pass",
    "Finding": "",
    "Recommendation": "See roadmap"
  },
  {
    "ASVS": "v5.0.0-6.4.3",
    "Level": 2,
    "Chapter": "Authentication",
    "Applicability": "Applicable L2",
    "Component": "Starlim ERP",
    "Verification": "automated/manual evidence where available",
    "Status": "NOT_TESTED",
    "Evidence": "No direct evidence in this pass",
    "Finding": "",
    "Recommendation": "See roadmap"
  },
  {
    "ASVS": "v5.0.0-6.4.4",
    "Level": 2,
    "Chapter": "Authentication",
    "Applicability": "Applicable L2",
    "Component": "Starlim ERP",
    "Verification": "automated/manual evidence where available",
    "Status": "NOT_TESTED",
    "Evidence": "No direct evidence in this pass",
    "Finding": "",
    "Recommendation": "See roadmap"
  },
  {
    "ASVS": "v5.0.0-6.5.1",
    "Level": 2,
    "Chapter": "Authentication",
    "Applicability": "Applicable L2",
    "Component": "Starlim ERP",
    "Verification": "automated/manual evidence where available",
    "Status": "NOT_TESTED",
    "Evidence": "No direct evidence in this pass",
    "Finding": "",
    "Recommendation": "See roadmap"
  },
  {
    "ASVS": "v5.0.0-6.5.2",
    "Level": 2,
    "Chapter": "Authentication",
    "Applicability": "Applicable L2",
    "Component": "Starlim ERP",
    "Verification": "automated/manual evidence where available",
    "Status": "NOT_TESTED",
    "Evidence": "No direct evidence in this pass",
    "Finding": "",
    "Recommendation": "See roadmap"
  },
  {
    "ASVS": "v5.0.0-6.5.3",
    "Level": 2,
    "Chapter": "Authentication",
    "Applicability": "Applicable L2",
    "Component": "Starlim ERP",
    "Verification": "automated/manual evidence where available",
    "Status": "NOT_TESTED",
    "Evidence": "No direct evidence in this pass",
    "Finding": "",
    "Recommendation": "See roadmap"
  },
  {
    "ASVS": "v5.0.0-6.5.4",
    "Level": 2,
    "Chapter": "Authentication",
    "Applicability": "Applicable L2",
    "Component": "Starlim ERP",
    "Verification": "automated/manual evidence where available",
    "Status": "NOT_TESTED",
    "Evidence": "No direct evidence in this pass",
    "Finding": "",
    "Recommendation": "See roadmap"
  },
  {
    "ASVS": "v5.0.0-6.5.5",
    "Level": 2,
    "Chapter": "Authentication",
    "Applicability": "Applicable L2",
    "Component": "Starlim ERP",
    "Verification": "automated/manual evidence where available",
    "Status": "NOT_TESTED",
    "Evidence": "No direct evidence in this pass",
    "Finding": "",
    "Recommendation": "See roadmap"
  },
  {
    "ASVS": "v5.0.0-6.6.1",
    "Level": 2,
    "Chapter": "Authentication",
    "Applicability": "Applicable L2",
    "Component": "Starlim ERP",
    "Verification": "automated/manual evidence where available",
    "Status": "NOT_TESTED",
    "Evidence": "No direct evidence in this pass",
    "Finding": "",
    "Recommendation": "See roadmap"
  },
  {
    "ASVS": "v5.0.0-6.6.2",
    "Level": 2,
    "Chapter": "Authentication",
    "Applicability": "Applicable L2",
    "Component": "Starlim ERP",
    "Verification": "automated/manual evidence where available",
    "Status": "NOT_TESTED",
    "Evidence": "No direct evidence in this pass",
    "Finding": "",
    "Recommendation": "See roadmap"
  },
  {
    "ASVS": "v5.0.0-6.6.3",
    "Level": 2,
    "Chapter": "Authentication",
    "Applicability": "Applicable L2",
    "Component": "Starlim ERP",
    "Verification": "automated/manual evidence where available",
    "Status": "NOT_TESTED",
    "Evidence": "No direct evidence in this pass",
    "Finding": "",
    "Recommendation": "See roadmap"
  },
  {
    "ASVS": "v5.0.0-6.8.1",
    "Level": 2,
    "Chapter": "Authentication",
    "Applicability": "Applicable L2",
    "Component": "Starlim ERP",
    "Verification": "automated/manual evidence where available",
    "Status": "NOT_TESTED",
    "Evidence": "No direct evidence in this pass",
    "Finding": "",
    "Recommendation": "See roadmap"
  },
  {
    "ASVS": "v5.0.0-6.8.2",
    "Level": 2,
    "Chapter": "Authentication",
    "Applicability": "Applicable L2",
    "Component": "Starlim ERP",
    "Verification": "automated/manual evidence where available",
    "Status": "NOT_TESTED",
    "Evidence": "No direct evidence in this pass",
    "Finding": "",
    "Recommendation": "See roadmap"
  },
  {
    "ASVS": "v5.0.0-6.8.3",
    "Level": 2,
    "Chapter": "Authentication",
    "Applicability": "Applicable L2",
    "Component": "Starlim ERP",
    "Verification": "automated/manual evidence where available",
    "Status": "NOT_TESTED",
    "Evidence": "No direct evidence in this pass",
    "Finding": "",
    "Recommendation": "See roadmap"
  },
  {
    "ASVS": "v5.0.0-6.8.4",
    "Level": 2,
    "Chapter": "Authentication",
    "Applicability": "Applicable L2",
    "Component": "Starlim ERP",
    "Verification": "automated/manual evidence where available",
    "Status": "NOT_TESTED",
    "Evidence": "No direct evidence in this pass",
    "Finding": "",
    "Recommendation": "See roadmap"
  },
  {
    "ASVS": "v5.0.0-7.1.1",
    "Level": 2,
    "Chapter": "Session Management",
    "Applicability": "Applicable L2",
    "Component": "Starlim ERP",
    "Verification": "automated/manual evidence where available",
    "Status": "NOT_TESTED",
    "Evidence": "No direct evidence in this pass",
    "Finding": "",
    "Recommendation": "See roadmap"
  },
  {
    "ASVS": "v5.0.0-7.1.2",
    "Level": 2,
    "Chapter": "Session Management",
    "Applicability": "Applicable L2",
    "Component": "Starlim ERP",
    "Verification": "automated/manual evidence where available",
    "Status": "NOT_TESTED",
    "Evidence": "No direct evidence in this pass",
    "Finding": "",
    "Recommendation": "See roadmap"
  },
  {
    "ASVS": "v5.0.0-7.1.3",
    "Level": 2,
    "Chapter": "Session Management",
    "Applicability": "Applicable L2",
    "Component": "Starlim ERP",
    "Verification": "automated/manual evidence where available",
    "Status": "NOT_TESTED",
    "Evidence": "No direct evidence in this pass",
    "Finding": "",
    "Recommendation": "See roadmap"
  },
  {
    "ASVS": "v5.0.0-7.3.1",
    "Level": 2,
    "Chapter": "Session Management",
    "Applicability": "Applicable L2",
    "Component": "Starlim ERP",
    "Verification": "automated/manual evidence where available",
    "Status": "NOT_TESTED",
    "Evidence": "No direct evidence in this pass",
    "Finding": "",
    "Recommendation": "See roadmap"
  },
  {
    "ASVS": "v5.0.0-7.3.2",
    "Level": 2,
    "Chapter": "Session Management",
    "Applicability": "Applicable L2",
    "Component": "Starlim ERP",
    "Verification": "automated/manual evidence where available",
    "Status": "NOT_TESTED",
    "Evidence": "No direct evidence in this pass",
    "Finding": "",
    "Recommendation": "See roadmap"
  },
  {
    "ASVS": "v5.0.0-7.4.3",
    "Level": 2,
    "Chapter": "Session Management",
    "Applicability": "Applicable L2",
    "Component": "Starlim ERP",
    "Verification": "automated/manual evidence where available",
    "Status": "NOT_TESTED",
    "Evidence": "No direct evidence in this pass",
    "Finding": "",
    "Recommendation": "See roadmap"
  },
  {
    "ASVS": "v5.0.0-7.4.4",
    "Level": 2,
    "Chapter": "Session Management",
    "Applicability": "Applicable L2",
    "Component": "Starlim ERP",
    "Verification": "automated/manual evidence where available",
    "Status": "NOT_TESTED",
    "Evidence": "No direct evidence in this pass",
    "Finding": "",
    "Recommendation": "See roadmap"
  },
  {
    "ASVS": "v5.0.0-7.4.5",
    "Level": 2,
    "Chapter": "Session Management",
    "Applicability": "Applicable L2",
    "Component": "Starlim ERP",
    "Verification": "automated/manual evidence where available",
    "Status": "NOT_TESTED",
    "Evidence": "No direct evidence in this pass",
    "Finding": "",
    "Recommendation": "See roadmap"
  },
  {
    "ASVS": "v5.0.0-7.5.1",
    "Level": 2,
    "Chapter": "Session Management",
    "Applicability": "Applicable L2",
    "Component": "Starlim ERP",
    "Verification": "automated/manual evidence where available",
    "Status": "NOT_TESTED",
    "Evidence": "No direct evidence in this pass",
    "Finding": "",
    "Recommendation": "See roadmap"
  },
  {
    "ASVS": "v5.0.0-7.5.2",
    "Level": 2,
    "Chapter": "Session Management",
    "Applicability": "Applicable L2",
    "Component": "Starlim ERP",
    "Verification": "automated/manual evidence where available",
    "Status": "NOT_TESTED",
    "Evidence": "No direct evidence in this pass",
    "Finding": "",
    "Recommendation": "See roadmap"
  },
  {
    "ASVS": "v5.0.0-7.6.1",
    "Level": 2,
    "Chapter": "Session Management",
    "Applicability": "Applicable L2",
    "Component": "Starlim ERP",
    "Verification": "automated/manual evidence where available",
    "Status": "NOT_TESTED",
    "Evidence": "No direct evidence in this pass",
    "Finding": "",
    "Recommendation": "See roadmap"
  },
  {
    "ASVS": "v5.0.0-7.6.2",
    "Level": 2,
    "Chapter": "Session Management",
    "Applicability": "Applicable L2",
    "Component": "Starlim ERP",
    "Verification": "automated/manual evidence where available",
    "Status": "NOT_TESTED",
    "Evidence": "No direct evidence in this pass",
    "Finding": "",
    "Recommendation": "See roadmap"
  },
  {
    "ASVS": "v5.0.0-8.1.2",
    "Level": 2,
    "Chapter": "Authorization",
    "Applicability": "Applicable L2",
    "Component": "Starlim ERP",
    "Verification": "automated/manual evidence where available",
    "Status": "NOT_TESTED",
    "Evidence": "No direct evidence in this pass",
    "Finding": "",
    "Recommendation": "See roadmap"
  },
  {
    "ASVS": "v5.0.0-8.2.3",
    "Level": 2,
    "Chapter": "Authorization",
    "Applicability": "Applicable L2",
    "Component": "Starlim ERP",
    "Verification": "automated/manual evidence where available",
    "Status": "NOT_TESTED",
    "Evidence": "No direct evidence in this pass",
    "Finding": "",
    "Recommendation": "See roadmap"
  },
  {
    "ASVS": "v5.0.0-8.4.1",
    "Level": 2,
    "Chapter": "Authorization",
    "Applicability": "Applicable L2",
    "Component": "Starlim ERP",
    "Verification": "automated/manual evidence where available",
    "Status": "NOT_TESTED",
    "Evidence": "No direct evidence in this pass",
    "Finding": "",
    "Recommendation": "See roadmap"
  },
  {
    "ASVS": "v5.0.0-9.2.2",
    "Level": 2,
    "Chapter": "Self-contained Tokens",
    "Applicability": "Applicable L2",
    "Component": "Starlim ERP",
    "Verification": "automated/manual evidence where available",
    "Status": "NOT_TESTED",
    "Evidence": "No direct evidence in this pass",
    "Finding": "",
    "Recommendation": "See roadmap"
  },
  {
    "ASVS": "v5.0.0-9.2.3",
    "Level": 2,
    "Chapter": "Self-contained Tokens",
    "Applicability": "Applicable L2",
    "Component": "Starlim ERP",
    "Verification": "automated/manual evidence where available",
    "Status": "NOT_TESTED",
    "Evidence": "No direct evidence in this pass",
    "Finding": "",
    "Recommendation": "See roadmap"
  },
  {
    "ASVS": "v5.0.0-9.2.4",
    "Level": 2,
    "Chapter": "Self-contained Tokens",
    "Applicability": "Applicable L2",
    "Component": "Starlim ERP",
    "Verification": "automated/manual evidence where available",
    "Status": "NOT_TESTED",
    "Evidence": "No direct evidence in this pass",
    "Finding": "",
    "Recommendation": "See roadmap"
  },
  {
    "ASVS": "v5.0.0-10.1.1",
    "Level": 2,
    "Chapter": "OAuth and OIDC",
    "Applicability": "Applicable L2",
    "Component": "Starlim ERP",
    "Verification": "automated/manual evidence where available",
    "Status": "NOT_TESTED",
    "Evidence": "No direct evidence in this pass",
    "Finding": "",
    "Recommendation": "See roadmap"
  },
  {
    "ASVS": "v5.0.0-10.1.2",
    "Level": 2,
    "Chapter": "OAuth and OIDC",
    "Applicability": "Applicable L2",
    "Component": "Starlim ERP",
    "Verification": "automated/manual evidence where available",
    "Status": "NOT_TESTED",
    "Evidence": "No direct evidence in this pass",
    "Finding": "",
    "Recommendation": "See roadmap"
  },
  {
    "ASVS": "v5.0.0-10.2.1",
    "Level": 2,
    "Chapter": "OAuth and OIDC",
    "Applicability": "Applicable L2",
    "Component": "Starlim ERP",
    "Verification": "automated/manual evidence where available",
    "Status": "NOT_TESTED",
    "Evidence": "No direct evidence in this pass",
    "Finding": "",
    "Recommendation": "See roadmap"
  },
  {
    "ASVS": "v5.0.0-10.2.2",
    "Level": 2,
    "Chapter": "OAuth and OIDC",
    "Applicability": "Applicable L2",
    "Component": "Starlim ERP",
    "Verification": "automated/manual evidence where available",
    "Status": "NOT_TESTED",
    "Evidence": "No direct evidence in this pass",
    "Finding": "",
    "Recommendation": "See roadmap"
  },
  {
    "ASVS": "v5.0.0-10.3.1",
    "Level": 2,
    "Chapter": "OAuth and OIDC",
    "Applicability": "Applicable L2",
    "Component": "Starlim ERP",
    "Verification": "automated/manual evidence where available",
    "Status": "NOT_TESTED",
    "Evidence": "No direct evidence in this pass",
    "Finding": "",
    "Recommendation": "See roadmap"
  },
  {
    "ASVS": "v5.0.0-10.3.2",
    "Level": 2,
    "Chapter": "OAuth and OIDC",
    "Applicability": "Applicable L2",
    "Component": "Starlim ERP",
    "Verification": "automated/manual evidence where available",
    "Status": "NOT_TESTED",
    "Evidence": "No direct evidence in this pass",
    "Finding": "",
    "Recommendation": "See roadmap"
  },
  {
    "ASVS": "v5.0.0-10.3.3",
    "Level": 2,
    "Chapter": "OAuth and OIDC",
    "Applicability": "Applicable L2",
    "Component": "Starlim ERP",
    "Verification": "automated/manual evidence where available",
    "Status": "NOT_TESTED",
    "Evidence": "No direct evidence in this pass",
    "Finding": "",
    "Recommendation": "See roadmap"
  },
  {
    "ASVS": "v5.0.0-10.3.4",
    "Level": 2,
    "Chapter": "OAuth and OIDC",
    "Applicability": "Applicable L2",
    "Component": "Starlim ERP",
    "Verification": "automated/manual evidence where available",
    "Status": "NOT_TESTED",
    "Evidence": "No direct evidence in this pass",
    "Finding": "",
    "Recommendation": "See roadmap"
  },
  {
    "ASVS": "v5.0.0-10.4.6",
    "Level": 2,
    "Chapter": "OAuth and OIDC",
    "Applicability": "Applicable L2",
    "Component": "Starlim ERP",
    "Verification": "automated/manual evidence where available",
    "Status": "NOT_TESTED",
    "Evidence": "No direct evidence in this pass",
    "Finding": "",
    "Recommendation": "See roadmap"
  },
  {
    "ASVS": "v5.0.0-10.4.7",
    "Level": 2,
    "Chapter": "OAuth and OIDC",
    "Applicability": "Applicable L2",
    "Component": "Starlim ERP",
    "Verification": "automated/manual evidence where available",
    "Status": "NOT_TESTED",
    "Evidence": "No direct evidence in this pass",
    "Finding": "",
    "Recommendation": "See roadmap"
  },
  {
    "ASVS": "v5.0.0-10.4.8",
    "Level": 2,
    "Chapter": "OAuth and OIDC",
    "Applicability": "Applicable L2",
    "Component": "Starlim ERP",
    "Verification": "automated/manual evidence where available",
    "Status": "NOT_TESTED",
    "Evidence": "No direct evidence in this pass",
    "Finding": "",
    "Recommendation": "See roadmap"
  },
  {
    "ASVS": "v5.0.0-10.4.9",
    "Level": 2,
    "Chapter": "OAuth and OIDC",
    "Applicability": "Applicable L2",
    "Component": "Starlim ERP",
    "Verification": "automated/manual evidence where available",
    "Status": "NOT_TESTED",
    "Evidence": "No direct evidence in this pass",
    "Finding": "",
    "Recommendation": "See roadmap"
  },
  {
    "ASVS": "v5.0.0-10.4.10",
    "Level": 2,
    "Chapter": "OAuth and OIDC",
    "Applicability": "Applicable L2",
    "Component": "Starlim ERP",
    "Verification": "automated/manual evidence where available",
    "Status": "NOT_TESTED",
    "Evidence": "No direct evidence in this pass",
    "Finding": "",
    "Recommendation": "See roadmap"
  },
  {
    "ASVS": "v5.0.0-10.4.11",
    "Level": 2,
    "Chapter": "OAuth and OIDC",
    "Applicability": "Applicable L2",
    "Component": "Starlim ERP",
    "Verification": "automated/manual evidence where available",
    "Status": "NOT_TESTED",
    "Evidence": "No direct evidence in this pass",
    "Finding": "",
    "Recommendation": "See roadmap"
  },
  {
    "ASVS": "v5.0.0-10.5.1",
    "Level": 2,
    "Chapter": "OAuth and OIDC",
    "Applicability": "Applicable L2",
    "Component": "Starlim ERP",
    "Verification": "automated/manual evidence where available",
    "Status": "NOT_TESTED",
    "Evidence": "No direct evidence in this pass",
    "Finding": "",
    "Recommendation": "See roadmap"
  },
  {
    "ASVS": "v5.0.0-10.5.2",
    "Level": 2,
    "Chapter": "OAuth and OIDC",
    "Applicability": "Applicable L2",
    "Component": "Starlim ERP",
    "Verification": "automated/manual evidence where available",
    "Status": "NOT_TESTED",
    "Evidence": "No direct evidence in this pass",
    "Finding": "",
    "Recommendation": "See roadmap"
  },
  {
    "ASVS": "v5.0.0-10.5.3",
    "Level": 2,
    "Chapter": "OAuth and OIDC",
    "Applicability": "Applicable L2",
    "Component": "Starlim ERP",
    "Verification": "automated/manual evidence where available",
    "Status": "NOT_TESTED",
    "Evidence": "No direct evidence in this pass",
    "Finding": "",
    "Recommendation": "See roadmap"
  },
  {
    "ASVS": "v5.0.0-10.5.4",
    "Level": 2,
    "Chapter": "OAuth and OIDC",
    "Applicability": "Applicable L2",
    "Component": "Starlim ERP",
    "Verification": "automated/manual evidence where available",
    "Status": "NOT_TESTED",
    "Evidence": "No direct evidence in this pass",
    "Finding": "",
    "Recommendation": "See roadmap"
  },
  {
    "ASVS": "v5.0.0-10.5.5",
    "Level": 2,
    "Chapter": "OAuth and OIDC",
    "Applicability": "Applicable L2",
    "Component": "Starlim ERP",
    "Verification": "automated/manual evidence where available",
    "Status": "NOT_TESTED",
    "Evidence": "No direct evidence in this pass",
    "Finding": "",
    "Recommendation": "See roadmap"
  },
  {
    "ASVS": "v5.0.0-10.6.1",
    "Level": 2,
    "Chapter": "OAuth and OIDC",
    "Applicability": "Applicable L2",
    "Component": "Starlim ERP",
    "Verification": "automated/manual evidence where available",
    "Status": "NOT_TESTED",
    "Evidence": "No direct evidence in this pass",
    "Finding": "",
    "Recommendation": "See roadmap"
  },
  {
    "ASVS": "v5.0.0-10.6.2",
    "Level": 2,
    "Chapter": "OAuth and OIDC",
    "Applicability": "Applicable L2",
    "Component": "Starlim ERP",
    "Verification": "automated/manual evidence where available",
    "Status": "NOT_TESTED",
    "Evidence": "No direct evidence in this pass",
    "Finding": "",
    "Recommendation": "See roadmap"
  },
  {
    "ASVS": "v5.0.0-10.7.1",
    "Level": 2,
    "Chapter": "OAuth and OIDC",
    "Applicability": "Applicable L2",
    "Component": "Starlim ERP",
    "Verification": "automated/manual evidence where available",
    "Status": "NOT_TESTED",
    "Evidence": "No direct evidence in this pass",
    "Finding": "",
    "Recommendation": "See roadmap"
  },
  {
    "ASVS": "v5.0.0-10.7.2",
    "Level": 2,
    "Chapter": "OAuth and OIDC",
    "Applicability": "Applicable L2",
    "Component": "Starlim ERP",
    "Verification": "automated/manual evidence where available",
    "Status": "NOT_TESTED",
    "Evidence": "No direct evidence in this pass",
    "Finding": "",
    "Recommendation": "See roadmap"
  },
  {
    "ASVS": "v5.0.0-10.7.3",
    "Level": 2,
    "Chapter": "OAuth and OIDC",
    "Applicability": "Applicable L2",
    "Component": "Starlim ERP",
    "Verification": "automated/manual evidence where available",
    "Status": "NOT_TESTED",
    "Evidence": "No direct evidence in this pass",
    "Finding": "",
    "Recommendation": "See roadmap"
  },
  {
    "ASVS": "v5.0.0-11.1.1",
    "Level": 2,
    "Chapter": "Cryptography",
    "Applicability": "Applicable L2",
    "Component": "Starlim ERP",
    "Verification": "automated/manual evidence where available",
    "Status": "NOT_TESTED",
    "Evidence": "No direct evidence in this pass",
    "Finding": "",
    "Recommendation": "See roadmap"
  },
  {
    "ASVS": "v5.0.0-11.1.2",
    "Level": 2,
    "Chapter": "Cryptography",
    "Applicability": "Applicable L2",
    "Component": "Starlim ERP",
    "Verification": "automated/manual evidence where available",
    "Status": "NOT_TESTED",
    "Evidence": "No direct evidence in this pass",
    "Finding": "",
    "Recommendation": "See roadmap"
  },
  {
    "ASVS": "v5.0.0-11.2.1",
    "Level": 2,
    "Chapter": "Cryptography",
    "Applicability": "Applicable L2",
    "Component": "Starlim ERP",
    "Verification": "automated/manual evidence where available",
    "Status": "NOT_TESTED",
    "Evidence": "No direct evidence in this pass",
    "Finding": "",
    "Recommendation": "See roadmap"
  },
  {
    "ASVS": "v5.0.0-11.2.2",
    "Level": 2,
    "Chapter": "Cryptography",
    "Applicability": "Applicable L2",
    "Component": "Starlim ERP",
    "Verification": "automated/manual evidence where available",
    "Status": "NOT_TESTED",
    "Evidence": "No direct evidence in this pass",
    "Finding": "",
    "Recommendation": "See roadmap"
  },
  {
    "ASVS": "v5.0.0-11.2.3",
    "Level": 2,
    "Chapter": "Cryptography",
    "Applicability": "Applicable L2",
    "Component": "Starlim ERP",
    "Verification": "automated/manual evidence where available",
    "Status": "NOT_TESTED",
    "Evidence": "No direct evidence in this pass",
    "Finding": "",
    "Recommendation": "See roadmap"
  },
  {
    "ASVS": "v5.0.0-11.3.3",
    "Level": 2,
    "Chapter": "Cryptography",
    "Applicability": "Applicable L2",
    "Component": "Starlim ERP",
    "Verification": "automated/manual evidence where available",
    "Status": "NOT_TESTED",
    "Evidence": "No direct evidence in this pass",
    "Finding": "",
    "Recommendation": "See roadmap"
  },
  {
    "ASVS": "v5.0.0-11.4.2",
    "Level": 2,
    "Chapter": "Cryptography",
    "Applicability": "Applicable L2",
    "Component": "Starlim ERP",
    "Verification": "automated/manual evidence where available",
    "Status": "NOT_TESTED",
    "Evidence": "No direct evidence in this pass",
    "Finding": "",
    "Recommendation": "See roadmap"
  },
  {
    "ASVS": "v5.0.0-11.4.3",
    "Level": 2,
    "Chapter": "Cryptography",
    "Applicability": "Applicable L2",
    "Component": "Starlim ERP",
    "Verification": "automated/manual evidence where available",
    "Status": "NOT_TESTED",
    "Evidence": "No direct evidence in this pass",
    "Finding": "",
    "Recommendation": "See roadmap"
  },
  {
    "ASVS": "v5.0.0-11.4.4",
    "Level": 2,
    "Chapter": "Cryptography",
    "Applicability": "Applicable L2",
    "Component": "Starlim ERP",
    "Verification": "automated/manual evidence where available",
    "Status": "NOT_TESTED",
    "Evidence": "No direct evidence in this pass",
    "Finding": "",
    "Recommendation": "See roadmap"
  },
  {
    "ASVS": "v5.0.0-11.5.1",
    "Level": 2,
    "Chapter": "Cryptography",
    "Applicability": "Applicable L2",
    "Component": "Starlim ERP",
    "Verification": "automated/manual evidence where available",
    "Status": "NOT_TESTED",
    "Evidence": "No direct evidence in this pass",
    "Finding": "",
    "Recommendation": "See roadmap"
  },
  {
    "ASVS": "v5.0.0-11.6.1",
    "Level": 2,
    "Chapter": "Cryptography",
    "Applicability": "Applicable L2",
    "Component": "Starlim ERP",
    "Verification": "automated/manual evidence where available",
    "Status": "NOT_TESTED",
    "Evidence": "No direct evidence in this pass",
    "Finding": "",
    "Recommendation": "See roadmap"
  },
  {
    "ASVS": "v5.0.0-12.1.2",
    "Level": 2,
    "Chapter": "Secure Communication",
    "Applicability": "Applicable L2",
    "Component": "Starlim ERP",
    "Verification": "automated/manual evidence where available",
    "Status": "NOT_TESTED",
    "Evidence": "No direct evidence in this pass",
    "Finding": "",
    "Recommendation": "See roadmap"
  },
  {
    "ASVS": "v5.0.0-12.1.3",
    "Level": 2,
    "Chapter": "Secure Communication",
    "Applicability": "Applicable L2",
    "Component": "Starlim ERP",
    "Verification": "automated/manual evidence where available",
    "Status": "NOT_TESTED",
    "Evidence": "No direct evidence in this pass",
    "Finding": "",
    "Recommendation": "See roadmap"
  },
  {
    "ASVS": "v5.0.0-12.3.1",
    "Level": 2,
    "Chapter": "Secure Communication",
    "Applicability": "Applicable L2",
    "Component": "Starlim ERP",
    "Verification": "automated/manual evidence where available",
    "Status": "NOT_TESTED",
    "Evidence": "No direct evidence in this pass",
    "Finding": "",
    "Recommendation": "See roadmap"
  },
  {
    "ASVS": "v5.0.0-12.3.2",
    "Level": 2,
    "Chapter": "Secure Communication",
    "Applicability": "Applicable L2",
    "Component": "Starlim ERP",
    "Verification": "automated/manual evidence where available",
    "Status": "NOT_TESTED",
    "Evidence": "No direct evidence in this pass",
    "Finding": "",
    "Recommendation": "See roadmap"
  },
  {
    "ASVS": "v5.0.0-12.3.3",
    "Level": 2,
    "Chapter": "Secure Communication",
    "Applicability": "Applicable L2",
    "Component": "Starlim ERP",
    "Verification": "automated/manual evidence where available",
    "Status": "NOT_TESTED",
    "Evidence": "No direct evidence in this pass",
    "Finding": "",
    "Recommendation": "See roadmap"
  },
  {
    "ASVS": "v5.0.0-12.3.4",
    "Level": 2,
    "Chapter": "Secure Communication",
    "Applicability": "Applicable L2",
    "Component": "Starlim ERP",
    "Verification": "automated/manual evidence where available",
    "Status": "NOT_TESTED",
    "Evidence": "No direct evidence in this pass",
    "Finding": "",
    "Recommendation": "See roadmap"
  },
  {
    "ASVS": "v5.0.0-13.1.1",
    "Level": 2,
    "Chapter": "Configuration",
    "Applicability": "Applicable L2",
    "Component": "Starlim ERP",
    "Verification": "automated/manual evidence where available",
    "Status": "NOT_TESTED",
    "Evidence": "No direct evidence in this pass",
    "Finding": "",
    "Recommendation": "See roadmap"
  },
  {
    "ASVS": "v5.0.0-13.2.1",
    "Level": 2,
    "Chapter": "Configuration",
    "Applicability": "Applicable L2",
    "Component": "Starlim ERP",
    "Verification": "automated/manual evidence where available",
    "Status": "NOT_TESTED",
    "Evidence": "No direct evidence in this pass",
    "Finding": "",
    "Recommendation": "See roadmap"
  },
  {
    "ASVS": "v5.0.0-13.2.2",
    "Level": 2,
    "Chapter": "Configuration",
    "Applicability": "Applicable L2",
    "Component": "Starlim ERP",
    "Verification": "automated/manual evidence where available",
    "Status": "NOT_TESTED",
    "Evidence": "No direct evidence in this pass",
    "Finding": "",
    "Recommendation": "See roadmap"
  },
  {
    "ASVS": "v5.0.0-13.2.3",
    "Level": 2,
    "Chapter": "Configuration",
    "Applicability": "Applicable L2",
    "Component": "Starlim ERP",
    "Verification": "automated/manual evidence where available",
    "Status": "NOT_TESTED",
    "Evidence": "No direct evidence in this pass",
    "Finding": "",
    "Recommendation": "See roadmap"
  },
  {
    "ASVS": "v5.0.0-13.2.4",
    "Level": 2,
    "Chapter": "Configuration",
    "Applicability": "Applicable L2",
    "Component": "Starlim ERP",
    "Verification": "automated/manual evidence where available",
    "Status": "NOT_TESTED",
    "Evidence": "No direct evidence in this pass",
    "Finding": "",
    "Recommendation": "See roadmap"
  },
  {
    "ASVS": "v5.0.0-13.2.5",
    "Level": 2,
    "Chapter": "Configuration",
    "Applicability": "Applicable L2",
    "Component": "Starlim ERP",
    "Verification": "automated/manual evidence where available",
    "Status": "NOT_TESTED",
    "Evidence": "No direct evidence in this pass",
    "Finding": "",
    "Recommendation": "See roadmap"
  },
  {
    "ASVS": "v5.0.0-13.3.1",
    "Level": 2,
    "Chapter": "Configuration",
    "Applicability": "Applicable L2",
    "Component": "Starlim ERP",
    "Verification": "automated/manual evidence where available",
    "Status": "NOT_TESTED",
    "Evidence": "No direct evidence in this pass",
    "Finding": "",
    "Recommendation": "See roadmap"
  },
  {
    "ASVS": "v5.0.0-13.3.2",
    "Level": 2,
    "Chapter": "Configuration",
    "Applicability": "Applicable L2",
    "Component": "Starlim ERP",
    "Verification": "automated/manual evidence where available",
    "Status": "NOT_TESTED",
    "Evidence": "No direct evidence in this pass",
    "Finding": "",
    "Recommendation": "See roadmap"
  },
  {
    "ASVS": "v5.0.0-13.4.2",
    "Level": 2,
    "Chapter": "Configuration",
    "Applicability": "Applicable L2",
    "Component": "Starlim ERP",
    "Verification": "automated/manual evidence where available",
    "Status": "NOT_TESTED",
    "Evidence": "No direct evidence in this pass",
    "Finding": "",
    "Recommendation": "See roadmap"
  },
  {
    "ASVS": "v5.0.0-13.4.3",
    "Level": 2,
    "Chapter": "Configuration",
    "Applicability": "Applicable L2",
    "Component": "Starlim ERP",
    "Verification": "automated/manual evidence where available",
    "Status": "NOT_TESTED",
    "Evidence": "No direct evidence in this pass",
    "Finding": "",
    "Recommendation": "See roadmap"
  },
  {
    "ASVS": "v5.0.0-13.4.4",
    "Level": 2,
    "Chapter": "Configuration",
    "Applicability": "Applicable L2",
    "Component": "Starlim ERP",
    "Verification": "automated/manual evidence where available",
    "Status": "NOT_TESTED",
    "Evidence": "No direct evidence in this pass",
    "Finding": "",
    "Recommendation": "See roadmap"
  },
  {
    "ASVS": "v5.0.0-13.4.5",
    "Level": 2,
    "Chapter": "Configuration",
    "Applicability": "Applicable L2",
    "Component": "Starlim ERP",
    "Verification": "automated/manual evidence where available",
    "Status": "NOT_TESTED",
    "Evidence": "No direct evidence in this pass",
    "Finding": "",
    "Recommendation": "See roadmap"
  },
  {
    "ASVS": "v5.0.0-14.1.1",
    "Level": 2,
    "Chapter": "Data Protection",
    "Applicability": "Applicable L2",
    "Component": "Starlim ERP",
    "Verification": "automated/manual evidence where available",
    "Status": "NOT_TESTED",
    "Evidence": "No direct evidence in this pass",
    "Finding": "",
    "Recommendation": "See roadmap"
  },
  {
    "ASVS": "v5.0.0-14.1.2",
    "Level": 2,
    "Chapter": "Data Protection",
    "Applicability": "Applicable L2",
    "Component": "Starlim ERP",
    "Verification": "automated/manual evidence where available",
    "Status": "NOT_TESTED",
    "Evidence": "No direct evidence in this pass",
    "Finding": "",
    "Recommendation": "See roadmap"
  },
  {
    "ASVS": "v5.0.0-14.2.2",
    "Level": 2,
    "Chapter": "Data Protection",
    "Applicability": "Applicable L2",
    "Component": "Starlim ERP",
    "Verification": "automated/manual evidence where available",
    "Status": "NOT_TESTED",
    "Evidence": "No direct evidence in this pass",
    "Finding": "",
    "Recommendation": "See roadmap"
  },
  {
    "ASVS": "v5.0.0-14.2.3",
    "Level": 2,
    "Chapter": "Data Protection",
    "Applicability": "Applicable L2",
    "Component": "Starlim ERP",
    "Verification": "automated/manual evidence where available",
    "Status": "NOT_TESTED",
    "Evidence": "No direct evidence in this pass",
    "Finding": "",
    "Recommendation": "See roadmap"
  },
  {
    "ASVS": "v5.0.0-14.2.4",
    "Level": 2,
    "Chapter": "Data Protection",
    "Applicability": "Applicable L2",
    "Component": "Starlim ERP",
    "Verification": "automated/manual evidence where available",
    "Status": "NOT_TESTED",
    "Evidence": "No direct evidence in this pass",
    "Finding": "",
    "Recommendation": "See roadmap"
  },
  {
    "ASVS": "v5.0.0-14.3.2",
    "Level": 2,
    "Chapter": "Data Protection",
    "Applicability": "Applicable L2",
    "Component": "Starlim ERP",
    "Verification": "automated/manual evidence where available",
    "Status": "NOT_TESTED",
    "Evidence": "No direct evidence in this pass",
    "Finding": "",
    "Recommendation": "See roadmap"
  },
  {
    "ASVS": "v5.0.0-14.3.3",
    "Level": 2,
    "Chapter": "Data Protection",
    "Applicability": "Applicable L2",
    "Component": "Starlim ERP",
    "Verification": "automated/manual evidence where available",
    "Status": "NOT_TESTED",
    "Evidence": "No direct evidence in this pass",
    "Finding": "",
    "Recommendation": "See roadmap"
  },
  {
    "ASVS": "v5.0.0-15.1.2",
    "Level": 2,
    "Chapter": "Secure Coding and Architecture",
    "Applicability": "Applicable L2",
    "Component": "Starlim ERP",
    "Verification": "automated/manual evidence where available",
    "Status": "NOT_TESTED",
    "Evidence": "No direct evidence in this pass",
    "Finding": "",
    "Recommendation": "See roadmap"
  },
  {
    "ASVS": "v5.0.0-15.1.3",
    "Level": 2,
    "Chapter": "Secure Coding and Architecture",
    "Applicability": "Applicable L2",
    "Component": "Starlim ERP",
    "Verification": "automated/manual evidence where available",
    "Status": "NOT_TESTED",
    "Evidence": "No direct evidence in this pass",
    "Finding": "",
    "Recommendation": "See roadmap"
  },
  {
    "ASVS": "v5.0.0-15.2.2",
    "Level": 2,
    "Chapter": "Secure Coding and Architecture",
    "Applicability": "Applicable L2",
    "Component": "Starlim ERP",
    "Verification": "automated/manual evidence where available",
    "Status": "NOT_TESTED",
    "Evidence": "No direct evidence in this pass",
    "Finding": "",
    "Recommendation": "See roadmap"
  },
  {
    "ASVS": "v5.0.0-15.2.3",
    "Level": 2,
    "Chapter": "Secure Coding and Architecture",
    "Applicability": "Applicable L2",
    "Component": "Starlim ERP",
    "Verification": "automated/manual evidence where available",
    "Status": "NOT_TESTED",
    "Evidence": "No direct evidence in this pass",
    "Finding": "",
    "Recommendation": "See roadmap"
  },
  {
    "ASVS": "v5.0.0-15.3.2",
    "Level": 2,
    "Chapter": "Secure Coding and Architecture",
    "Applicability": "Applicable L2",
    "Component": "Starlim ERP",
    "Verification": "automated/manual evidence where available",
    "Status": "NOT_TESTED",
    "Evidence": "No direct evidence in this pass",
    "Finding": "",
    "Recommendation": "See roadmap"
  },
  {
    "ASVS": "v5.0.0-15.3.3",
    "Level": 2,
    "Chapter": "Secure Coding and Architecture",
    "Applicability": "Applicable L2",
    "Component": "Starlim ERP",
    "Verification": "automated/manual evidence where available",
    "Status": "NOT_TESTED",
    "Evidence": "No direct evidence in this pass",
    "Finding": "",
    "Recommendation": "See roadmap"
  },
  {
    "ASVS": "v5.0.0-15.3.4",
    "Level": 2,
    "Chapter": "Secure Coding and Architecture",
    "Applicability": "Applicable L2",
    "Component": "Starlim ERP",
    "Verification": "automated/manual evidence where available",
    "Status": "NOT_TESTED",
    "Evidence": "No direct evidence in this pass",
    "Finding": "",
    "Recommendation": "See roadmap"
  },
  {
    "ASVS": "v5.0.0-15.3.5",
    "Level": 2,
    "Chapter": "Secure Coding and Architecture",
    "Applicability": "Applicable L2",
    "Component": "Starlim ERP",
    "Verification": "automated/manual evidence where available",
    "Status": "NOT_TESTED",
    "Evidence": "No direct evidence in this pass",
    "Finding": "",
    "Recommendation": "See roadmap"
  },
  {
    "ASVS": "v5.0.0-15.3.6",
    "Level": 2,
    "Chapter": "Secure Coding and Architecture",
    "Applicability": "Applicable L2",
    "Component": "Starlim ERP",
    "Verification": "automated/manual evidence where available",
    "Status": "NOT_TESTED",
    "Evidence": "No direct evidence in this pass",
    "Finding": "",
    "Recommendation": "See roadmap"
  },
  {
    "ASVS": "v5.0.0-15.3.7",
    "Level": 2,
    "Chapter": "Secure Coding and Architecture",
    "Applicability": "Applicable L2",
    "Component": "Starlim ERP",
    "Verification": "automated/manual evidence where available",
    "Status": "NOT_TESTED",
    "Evidence": "No direct evidence in this pass",
    "Finding": "",
    "Recommendation": "See roadmap"
  },
  {
    "ASVS": "v5.0.0-16.1.1",
    "Level": 2,
    "Chapter": "Security Logging and Error Handling",
    "Applicability": "Applicable L2",
    "Component": "Starlim ERP",
    "Verification": "automated/manual evidence where available",
    "Status": "NOT_TESTED",
    "Evidence": "No direct evidence in this pass",
    "Finding": "",
    "Recommendation": "See roadmap"
  },
  {
    "ASVS": "v5.0.0-16.2.1",
    "Level": 2,
    "Chapter": "Security Logging and Error Handling",
    "Applicability": "Applicable L2",
    "Component": "Starlim ERP",
    "Verification": "automated/manual evidence where available",
    "Status": "NOT_TESTED",
    "Evidence": "No direct evidence in this pass",
    "Finding": "",
    "Recommendation": "See roadmap"
  },
  {
    "ASVS": "v5.0.0-16.2.2",
    "Level": 2,
    "Chapter": "Security Logging and Error Handling",
    "Applicability": "Applicable L2",
    "Component": "Starlim ERP",
    "Verification": "automated/manual evidence where available",
    "Status": "NOT_TESTED",
    "Evidence": "No direct evidence in this pass",
    "Finding": "",
    "Recommendation": "See roadmap"
  },
  {
    "ASVS": "v5.0.0-16.2.3",
    "Level": 2,
    "Chapter": "Security Logging and Error Handling",
    "Applicability": "Applicable L2",
    "Component": "Starlim ERP",
    "Verification": "automated/manual evidence where available",
    "Status": "NOT_TESTED",
    "Evidence": "No direct evidence in this pass",
    "Finding": "",
    "Recommendation": "See roadmap"
  },
  {
    "ASVS": "v5.0.0-16.2.4",
    "Level": 2,
    "Chapter": "Security Logging and Error Handling",
    "Applicability": "Applicable L2",
    "Component": "Starlim ERP",
    "Verification": "automated/manual evidence where available",
    "Status": "NOT_TESTED",
    "Evidence": "No direct evidence in this pass",
    "Finding": "",
    "Recommendation": "See roadmap"
  },
  {
    "ASVS": "v5.0.0-16.2.5",
    "Level": 2,
    "Chapter": "Security Logging and Error Handling",
    "Applicability": "Applicable L2",
    "Component": "Starlim ERP",
    "Verification": "automated/manual evidence where available",
    "Status": "NOT_TESTED",
    "Evidence": "No direct evidence in this pass",
    "Finding": "",
    "Recommendation": "See roadmap"
  },
  {
    "ASVS": "v5.0.0-16.3.1",
    "Level": 2,
    "Chapter": "Security Logging and Error Handling",
    "Applicability": "Applicable L2",
    "Component": "Starlim ERP",
    "Verification": "automated/manual evidence where available",
    "Status": "NOT_TESTED",
    "Evidence": "No direct evidence in this pass",
    "Finding": "",
    "Recommendation": "See roadmap"
  },
  {
    "ASVS": "v5.0.0-16.3.2",
    "Level": 2,
    "Chapter": "Security Logging and Error Handling",
    "Applicability": "Applicable L2",
    "Component": "Starlim ERP",
    "Verification": "automated/manual evidence where available",
    "Status": "NOT_TESTED",
    "Evidence": "No direct evidence in this pass",
    "Finding": "",
    "Recommendation": "See roadmap"
  },
  {
    "ASVS": "v5.0.0-16.3.3",
    "Level": 2,
    "Chapter": "Security Logging and Error Handling",
    "Applicability": "Applicable L2",
    "Component": "Starlim ERP",
    "Verification": "automated/manual evidence where available",
    "Status": "NOT_TESTED",
    "Evidence": "No direct evidence in this pass",
    "Finding": "",
    "Recommendation": "See roadmap"
  },
  {
    "ASVS": "v5.0.0-16.3.4",
    "Level": 2,
    "Chapter": "Security Logging and Error Handling",
    "Applicability": "Applicable L2",
    "Component": "Starlim ERP",
    "Verification": "automated/manual evidence where available",
    "Status": "NOT_TESTED",
    "Evidence": "No direct evidence in this pass",
    "Finding": "",
    "Recommendation": "See roadmap"
  },
  {
    "ASVS": "v5.0.0-16.4.1",
    "Level": 2,
    "Chapter": "Security Logging and Error Handling",
    "Applicability": "Applicable L2",
    "Component": "Starlim ERP",
    "Verification": "automated/manual evidence where available",
    "Status": "NOT_TESTED",
    "Evidence": "No direct evidence in this pass",
    "Finding": "",
    "Recommendation": "See roadmap"
  },
  {
    "ASVS": "v5.0.0-16.4.2",
    "Level": 2,
    "Chapter": "Security Logging and Error Handling",
    "Applicability": "Applicable L2",
    "Component": "Starlim ERP",
    "Verification": "automated/manual evidence where available",
    "Status": "NOT_TESTED",
    "Evidence": "No direct evidence in this pass",
    "Finding": "",
    "Recommendation": "See roadmap"
  },
  {
    "ASVS": "v5.0.0-16.4.3",
    "Level": 2,
    "Chapter": "Security Logging and Error Handling",
    "Applicability": "Applicable L2",
    "Component": "Starlim ERP",
    "Verification": "automated/manual evidence where available",
    "Status": "NOT_TESTED",
    "Evidence": "No direct evidence in this pass",
    "Finding": "",
    "Recommendation": "See roadmap"
  },
  {
    "ASVS": "v5.0.0-16.5.1",
    "Level": 2,
    "Chapter": "Security Logging and Error Handling",
    "Applicability": "Applicable L2",
    "Component": "Starlim ERP",
    "Verification": "automated/manual evidence where available",
    "Status": "NOT_TESTED",
    "Evidence": "No direct evidence in this pass",
    "Finding": "",
    "Recommendation": "See roadmap"
  },
  {
    "ASVS": "v5.0.0-16.5.2",
    "Level": 2,
    "Chapter": "Security Logging and Error Handling",
    "Applicability": "Applicable L2",
    "Component": "Starlim ERP",
    "Verification": "automated/manual evidence where available",
    "Status": "NOT_TESTED",
    "Evidence": "No direct evidence in this pass",
    "Finding": "",
    "Recommendation": "See roadmap"
  },
  {
    "ASVS": "v5.0.0-16.5.3",
    "Level": 2,
    "Chapter": "Security Logging and Error Handling",
    "Applicability": "Applicable L2",
    "Component": "Starlim ERP",
    "Verification": "automated/manual evidence where available",
    "Status": "NOT_TESTED",
    "Evidence": "No direct evidence in this pass",
    "Finding": "",
    "Recommendation": "See roadmap"
  },
  {
    "ASVS": "v5.0.0-17.1.1",
    "Level": 2,
    "Chapter": "WebRTC",
    "Applicability": "Applicable L2",
    "Component": "Starlim ERP",
    "Verification": "automated/manual evidence where available",
    "Status": "NOT_TESTED",
    "Evidence": "No direct evidence in this pass",
    "Finding": "",
    "Recommendation": "See roadmap"
  },
  {
    "ASVS": "v5.0.0-17.2.1",
    "Level": 2,
    "Chapter": "WebRTC",
    "Applicability": "Applicable L2",
    "Component": "Starlim ERP",
    "Verification": "automated/manual evidence where available",
    "Status": "NOT_TESTED",
    "Evidence": "No direct evidence in this pass",
    "Finding": "",
    "Recommendation": "See roadmap"
  },
  {
    "ASVS": "v5.0.0-17.2.2",
    "Level": 2,
    "Chapter": "WebRTC",
    "Applicability": "Applicable L2",
    "Component": "Starlim ERP",
    "Verification": "automated/manual evidence where available",
    "Status": "NOT_TESTED",
    "Evidence": "No direct evidence in this pass",
    "Finding": "",
    "Recommendation": "See roadmap"
  },
  {
    "ASVS": "v5.0.0-17.2.3",
    "Level": 2,
    "Chapter": "WebRTC",
    "Applicability": "Applicable L2",
    "Component": "Starlim ERP",
    "Verification": "automated/manual evidence where available",
    "Status": "NOT_TESTED",
    "Evidence": "No direct evidence in this pass",
    "Finding": "",
    "Recommendation": "See roadmap"
  },
  {
    "ASVS": "v5.0.0-17.2.4",
    "Level": 2,
    "Chapter": "WebRTC",
    "Applicability": "Applicable L2",
    "Component": "Starlim ERP",
    "Verification": "automated/manual evidence where available",
    "Status": "NOT_TESTED",
    "Evidence": "No direct evidence in this pass",
    "Finding": "",
    "Recommendation": "See roadmap"
  },
  {
    "ASVS": "v5.0.0-17.3.1",
    "Level": 2,
    "Chapter": "WebRTC",
    "Applicability": "Applicable L2",
    "Component": "Starlim ERP",
    "Verification": "automated/manual evidence where available",
    "Status": "NOT_TESTED",
    "Evidence": "No direct evidence in this pass",
    "Finding": "",
    "Recommendation": "See roadmap"
  },
  {
    "ASVS": "v5.0.0-17.3.2",
    "Level": 2,
    "Chapter": "WebRTC",
    "Applicability": "Applicable L2",
    "Component": "Starlim ERP",
    "Verification": "automated/manual evidence where available",
    "Status": "NOT_TESTED",
    "Evidence": "No direct evidence in this pass",
    "Finding": "",
    "Recommendation": "See roadmap"
  }
]